lk_moe/__init__.py
lk_moe/_dynamic_loader.py
lk_moe/_lk_moe_C.cpython-312-x86_64-linux-gnu.so
lk_moe/_lk_moe_C_avx2.so
lk_moe/_lk_moe_C_avx512.so
lk_moe/_lk_moe_C_avx512_amx.so
lk_moe/_version.py
lk_moe/py.typed
lk_moe.libs/libcuda-15c5e260.so.590.44.01
lk_moe.libs/libcudart-256e6409.so.12.9.79
lk_moe.libs/libggml-base-dc5d4372.so.0.9.4
lk_moe.libs/libggml-cpu-83073c85.so.0.9.4
lk_moe.libs/libggml-e7c25796.so.0.9.4
lk_moe.libs/libgomp-b18a813f.so.1.0.0
lk_moe.libs/libllama-1d0a978f.so.0.0.7503
lk_moe.libs/libnuma-f4824650.so.1.0.0
lk_moe-1.6.7.dist-info/METADATA
lk_moe-1.6.7.dist-info/WHEEL
lk_moe-1.6.7.dist-info/top_level.txt
lk_moe-1.6.7.dist-info/RECORD
lk_moe-1.6.7.dist-info/licenses/LICENSE
lk_moe-1.6.7.dist-info/licenses/THIRD_PARTY_LICENSES
lk_moe-1.6.7.dist-info/sboms/auditwheel.cdx.json
