Metadata-Version: 2.4
Name: lk_moe
Version: 1.6.7
Summary: lk_moe is a special NUMA extension of vllm that makes full use of CPU and memory resources, reduces GPU memory requirements, and features an efficient GPU parallel and NUMA parallel architecture, supporting hybrid inference for MOE large models.
Requires-Python: >=3.10,<3.14
License-File: LICENSE
License-File: THIRD_PARTY_LICENSES
Dynamic: license-file
Dynamic: requires-python
